matrix_registration/__init__.py
matrix_registration/api.py
matrix_registration/app.py
matrix_registration/config.py
matrix_registration/constants.py
matrix_registration/matrix_api.py
matrix_registration/tokens.py
matrix_registration/translation.py
matrix_registration/wordlist.txt
matrix_registration/static/css/style.css
matrix_registration/static/fonts/Nunito_400_Nunito_700.woff2
matrix_registration/static/images/element-logo.png
matrix_registration/static/images/favicon.ico
matrix_registration/static/images/icon.png
matrix_registration/static/images/icon32x32.png
matrix_registration/static/images/riot.png
matrix_registration/static/images/tile.png
matrix_registration/static/images/valley.jpg
matrix_registration/templates/register.html
matrix_registration/translations/messages.de.yaml
matrix_registration/translations/messages.en.yaml
matrix_registration/translations/messages.pt_BR.yaml
matrix_registration/translations/messages.zh_Hans.yaml
matrix_registration-0.9.1.post1.data/data/alembic.ini
matrix_registration-0.9.1.post1.data/data/alembic/env.py
matrix_registration-0.9.1.post1.data/data/alembic/versions/140a25d5f185_create_tokens_table.py
matrix_registration-0.9.1.post1.data/data/config/config.sample.yaml
matrix_registration-0.9.1.post1.dist-info/LICENSE
matrix_registration-0.9.1.post1.dist-info/METADATA
matrix_registration-0.9.1.post1.dist-info/WHEEL
matrix_registration-0.9.1.post1.dist-info/entry_points.txt
matrix_registration-0.9.1.post1.dist-info/top_level.txt
matrix_registration-0.9.1.post1.dist-info/RECORD
