Metadata-Version: 2.1
Name: matrix-registration
Version: 0.9.1.post1
Summary: token based matrix registration app
Home-page: https://github.com/zeratax/matrix-registration
Author: Jona Abdinghoff (ZerataX)
Author-email: mail@zera.tax
License: UNKNOWN
Platform: UNKNOWN
Classifier: Development Status :: 4 - Beta
Classifier: Topic :: Communications :: Chat
Classifier: License :: OSI Approved :: MIT License
Classifier: Programming Language :: Python :: 3.7
Classifier: Programming Language :: Python :: 3.8
Classifier: Programming Language :: Python :: 3.9
Requires-Python: ~=3.7
Requires-Dist: alembic (>=1.3.2)
Requires-Dist: appdirs (~=1.4.3)
Requires-Dist: Flask (~=1.1)
Requires-Dist: Flask-SQLAlchemy (~=2.4.1)
Requires-Dist: flask-cors (~=3.0.7)
Requires-Dist: flask-httpauth (>=3.3.0)
Requires-Dist: flask-limiter (>=1.1.0)
Requires-Dist: PyYAML (~=5.1)
Requires-Dist: requests (>=2.22)
Requires-Dist: SQLAlchemy (<1.4,>=1.3.13)
Requires-Dist: waitress (~=1.4.4)
Requires-Dist: WTForms (~=2.1)
Provides-Extra: postgres
Requires-Dist: psycopg2-binary (>=2.8.4) ; extra == 'postgres'
Provides-Extra: testing
Requires-Dist: parameterized (>=0.7.0) ; extra == 'testing'
Requires-Dist: flake8 (>=3.7.7) ; extra == 'testing'
